funkapi/__init__.py
funkapi/api.py
funkapi-0.1.5.dist-info/LICENSE.md
funkapi-0.1.5.dist-info/METADATA
funkapi-0.1.5.dist-info/WHEEL
funkapi-0.1.5.dist-info/top_level.txt
funkapi-0.1.5.dist-info/RECORD
