Metadata-Version: 2.1
Name: funkapi
Version: 0.1.5
Summary: Reverse engineered API of Freenet FUNK
Home-page: https://github.com/lagmoellertim/freenet-funk-api
Author: Tim-Luca Lagmöller
Author-email: hello@lagmoellertim.de
License: MIT License
Platform: UNKNOWN
Classifier: Programming Language :: Python :: 3
Classifier: License :: OSI Approved :: MIT License
Classifier: Operating System :: OS Independent
Requires-Dist: boto3 (==1.9.145)
Requires-Dist: botocore (==1.12.145)
Requires-Dist: certifi (==2019.3.9)
Requires-Dist: chardet (==3.0.4)
Requires-Dist: docutils (==0.14)
Requires-Dist: ecdsa (==0.13.2)
Requires-Dist: envs (==1.3)
Requires-Dist: future (==0.17.1)
Requires-Dist: idna (==2.8)
Requires-Dist: jmespath (==0.9.4)
Requires-Dist: pycryptodome (==3.3.1)
Requires-Dist: python-dateutil (==2.8.0)
Requires-Dist: python-jose-cryptodome (==1.3.2)
Requires-Dist: requests (==2.21.0)
Requires-Dist: s3transfer (==0.2.0)
Requires-Dist: six (==1.12.0)
Requires-Dist: urllib3 (==1.24.3)
Requires-Dist: warrant (==0.6.1)
